[
  {
    "criteriaEmphases": [
      {
        "criteriaEmphasis": 30, 
        "indicator": {
          "displayName": "Deads", 
          "iconResource": "http://crisma.cismet.de/resources/pilotE/todo_16.png", 
          "unit": "people", 
          "value": 156
        }
      }, 
      {
        "criteriaEmphasis": 100, 
        "indicator": {
          "displayName": "Cost", 
          "iconResource": "http://crisma.cismet.de/resources/pilotE/todo_16.png", 
          "unit": "Euro", 
          "value": 19384729
        }
      }, 
      {
        "criteriaEmphasis": 30, 
        "indicator": {
          "displayName": "Buildings", 
          "iconResource": "http://crisma.cismet.de/resources/pilotE/todo_16.png", 
          "unit": "buildings", 
          "value": 2091
        }
      }
    ], 
    "name": "care about cost", 
    "satisfactionEmphasis": [
      0.3333333333333333, 
      0.3333333333333333, 
      0.3333333333333333
    ]
  }, 
  {
    "criteriaEmphases": [
      {
        "criteriaEmphasis": 30, 
        "indicator": {
          "displayName": "Deads", 
          "iconResource": "http://crisma.cismet.de/resources/pilotE/todo_16.png", 
          "unit": "people", 
          "value": 156
        }
      }, 
      {
        "criteriaEmphasis": 30, 
        "indicator": {
          "displayName": "Cost", 
          "iconResource": "http://crisma.cismet.de/resources/pilotE/todo_16.png", 
          "unit": "Euro", 
          "value": 19384729
        }
      }, 
      {
        "criteriaEmphasis": 100, 
        "indicator": {
          "displayName": "Buildings", 
          "iconResource": "http://crisma.cismet.de/resources/pilotE/todo_16.png", 
          "unit": "buildings", 
          "value": 2091
        }
      }
    ], 
    "name": "care about buildings", 
    "satisfactionEmphasis": [
      0.3333333333333333, 
      0.3333333333333333, 
      0.3333333333333333
    ]
  }, 
  {
    "criteriaEmphases": [
      {
        "criteriaEmphasis": 100, 
        "indicator": {
          "displayName": "Deads", 
          "iconResource": "http://crisma.cismet.de/resources/pilotE/todo_16.png", 
          "unit": "people", 
          "value": 156
        }
      }, 
      {
        "criteriaEmphasis": 30, 
        "indicator": {
          "displayName": "Cost", 
          "iconResource": "http://crisma.cismet.de/resources/pilotE/todo_16.png", 
          "unit": "Euro", 
          "value": 19384729
        }
      }, 
      {
        "criteriaEmphasis": 30, 
        "indicator": {
          "displayName": "Buildings", 
          "iconResource": "http://crisma.cismet.de/resources/pilotE/todo_16.png", 
          "unit": "buildings", 
          "value": 2091
        }
      }
    ], 
    "name": "care about deads", 
    "satisfactionEmphasis": [
      0.3333333333333333, 
      0.3333333333333333, 
      0.3333333333333333
    ]
  }, 
  {
    "criteriaEmphases": [
      {
        "criteriaEmphasis": 100, 
        "indicator": {
          "displayName": "Deads", 
          "iconResource": "http://crisma.cismet.de/resources/pilotE/todo_16.png", 
          "unit": "people", 
          "value": 156
        }
      }, 
      {
        "criteriaEmphasis": 70, 
        "indicator": {
          "displayName": "Cost", 
          "iconResource": "http://crisma.cismet.de/resources/pilotE/todo_16.png", 
          "unit": "Euro", 
          "value": 19384729
        }
      }, 
      {
        "criteriaEmphasis": 85, 
        "indicator": {
          "displayName": "Buildings", 
          "iconResource": "http://crisma.cismet.de/resources/pilotE/todo_16.png", 
          "unit": "buildings", 
          "value": 2091
        }
      }
    ], 
    "name": "no compromise", 
    "satisfactionEmphasis": [
      0, 
      0, 
      1
    ]
  }, 
  {
    "criteriaEmphases": [
      {
        "criteriaEmphasis": 100, 
        "indicator": {
          "displayName": "Deads", 
          "iconResource": "http://crisma.cismet.de/resources/pilotE/todo_16.png", 
          "unit": "people", 
          "value": 156
        }
      }, 
      {
        "criteriaEmphasis": 100, 
        "indicator": {
          "displayName": "Cost", 
          "iconResource": "http://crisma.cismet.de/resources/pilotE/todo_16.png", 
          "unit": "Euro", 
          "value": 19384729
        }
      }, 
      {
        "criteriaEmphasis": 100, 
        "indicator": {
          "displayName": "Buildings", 
          "iconResource": "http://crisma.cismet.de/resources/pilotE/todo_16.png", 
          "unit": "buildings", 
          "value": 2091
        }
      }
    ], 
    "name": "at least get sth right", 
    "satisfactionEmphasis": [
      1, 
      0, 
      0
    ]
  }, 
  {
    "criteriaEmphases": [
      {
        "criteriaEmphasis": 100, 
        "indicator": {
          "displayName": "Deads", 
          "iconResource": "http://crisma.cismet.de/resources/pilotE/todo_16.png", 
          "unit": "people", 
          "value": 156
        }
      }, 
      {
        "criteriaEmphasis": 70, 
        "indicator": {
          "displayName": "Cost", 
          "iconResource": "http://crisma.cismet.de/resources/pilotE/todo_16.png", 
          "unit": "Euro", 
          "value": 19384729
        }
      }, 
      {
        "criteriaEmphasis": 85, 
        "indicator": {
          "displayName": "Buildings", 
          "iconResource": "http://crisma.cismet.de/resources/pilotE/todo_16.png", 
          "unit": "buildings", 
          "value": 2091
        }
      }
    ], 
    "name": "people care", 
    "satisfactionEmphasis": [
      0.03650450827484224, 
      0.24023200711490703, 
      0.7232634846102508
    ]
  }
]
